cegpy/__init__.py
cegpy/graphs/__init__.py
cegpy/graphs/_ceg.py
cegpy/graphs/_ceg_reducer.py
cegpy/trees/__init__.py
cegpy/trees/_event.py
cegpy/trees/_staged.py
cegpy/utilities/__init__.py
cegpy/utilities/_util.py
cegpy-1.1.0.dist-info/LICENSE
cegpy-1.1.0.dist-info/METADATA
cegpy-1.1.0.dist-info/WHEEL
cegpy-1.1.0.dist-info/top_level.txt
cegpy-1.1.0.dist-info/RECORD
