Metadata-Version: 2.1
Name: cegpy
Version: 1.1.0
Summary: Package for creating, manipulating, and analysing Chain Event Graphs. Built on networkx.
Home-page: https://github.com/g-walley/cegpy
Author: Gareth Walley
Author-email: gareth@walley.me
Project-URL: Bug Tracker, https://github.com/g-walley/cegpy/issues
Classifier: Programming Language :: Python :: 3
Classifier: License :: OSI Approved :: MIT License
Classifier: Operating System :: OS Independent
Requires-Python: >=3.9
License-File: LICENSE
Requires-Dist: pandas>=1.3.0
Requires-Dist: pydotplus>=2.0.2
Requires-Dist: ipython>=7.25.0
Requires-Dist: scipy>=1.7.0
Requires-Dist: colorutils>=0.3.0
Requires-Dist: networkx>=3.2.1
